distributions/Binomialdistribution.py
distributions/Gaussiandistribution.py
distributions/Generaldistribution.py
distributions/__init__.py
dsnd_probability_rvs-0.1.dist-info/DESCRIPTION.rst
dsnd_probability_rvs-0.1.dist-info/METADATA
dsnd_probability_rvs-0.1.dist-info/RECORD
dsnd_probability_rvs-0.1.dist-info/WHEEL
dsnd_probability_rvs-0.1.dist-info/metadata.json
dsnd_probability_rvs-0.1.dist-info/top_level.txt
