Metadata-Version: 2.0
Name: dsnd-probability-rvs
Version: 0.1
Summary: Gaussian and Binomial distributions
Home-page: UNKNOWN
Author: Rusen Gultekin
Author-email: rvsgltkn@hotmail.com
License: UNKNOWN
Platform: UNKNOWN
